pyvoog/__init__.py
pyvoog/app.py
pyvoog/args.py
pyvoog/configloader.py
pyvoog/controller/__init__.py
pyvoog/controller/api_base_controller.py
pyvoog/controller/controller.py
pyvoog/controller/util.py
pyvoog/db.py
pyvoog/exceptions.py
pyvoog/logging.py
pyvoog/model.py
pyvoog/router/__init__.py
pyvoog/router/endpoint.py
pyvoog/router/namespace.py
pyvoog/router/resource.py
pyvoog/router/router.py
pyvoog/router/util.py
pyvoog/server.py
pyvoog/signals.py
pyvoog/testing/controller_test_case.py
pyvoog/testing/signals.py
pyvoog/testing/test_runner.py
pyvoog/testing/util/__init__.py
pyvoog/testing/util/models.py
pyvoog/testing/util/requests.py
pyvoog/testing/util/util.py
pyvoog/user_agent.py
pyvoog/util/__init__.py
pyvoog/util/mapping.py
pyvoog/util/marshmallow.py
pyvoog/util/os.py
pyvoog/util/util.py
pyvoog/validatable.py
pyvoog/validations.py
pyvoog-0.5.6.dist-info/LICENSE
pyvoog-0.5.6.dist-info/METADATA
pyvoog-0.5.6.dist-info/WHEEL
pyvoog-0.5.6.dist-info/RECORD
